nphard_generators/__init__.py
nphard_generators/custom_factory.template
nphard_generators/graph_factory.py
nphard_generators/random_factory.py
nphard_generators/hamiltonian_cycle_problem/hcp_petersen_factory.py
nphard_generators/hamiltonian_cycle_problem/hcp_random_factory.py
nphard_generators/hamiltonian_cycle_problem/hcp_syn_h1_factory.py
nphard_generators/hamiltonian_cycle_problem/hcp_syn_h2_factory.py
nphard_generators/maximum_clique_problem/mcp_brock_factory.py
nphard_generators/maximum_clique_problem/mcp_cfat_factory.py
nphard_generators/maximum_clique_problem/mcp_hamming2_factory.py
nphard_generators/maximum_clique_problem/mcp_hamming3_factory.py
nphard_generators/maximum_clique_problem/mcp_hamming_factory.py
nphard_generators/maximum_clique_problem/mcp_random_factory.py
nphard_generators/maximum_clique_problem/mcp_sanchis_factory.py
nphard_generators/maximum_clique_problem/mcp_syn_a1_factory.py
nphard_generators/maximum_clique_problem/mcp_syn_a3_factory.py
nphard_generators/types/__init__.py
nphard_generators/types/graph_problem.py
nphard_generators/types/hamiltonian_cycle_problem/hc_problem.py
nphard_generators/types/hamiltonian_cycle_problem/hc_problem_simple_solution.py
nphard_generators/types/hamiltonian_cycle_problem/hc_problem_solution.py
nphard_generators/types/maximum_clique_problem/mc_problem.py
nphard_generators/types/maximum_clique_problem/mc_problem_simple_solution.py
nphard_generators/types/maximum_clique_problem/mc_problem_solution.py
nphard_generators-0.1.0.dist-info/METADATA
nphard_generators-0.1.0.dist-info/WHEEL
nphard_generators-0.1.0.dist-info/licenses/LICENSE
nphard_generators-0.1.0.dist-info/RECORD
