Metadata-Version: 2.4
Name: nphard-generators
Version: 0.1.0
Summary: Contains generators for np-hard problems with known solution.
Project-URL: Homepage, https://github.com/Jumagoro/nphard-generators
Project-URL: Issues, https://github.com/Jumagoro/nphard-generators/issues
Author-email: Gordian Hunecke <gogoh60@gmail.com>
License-Expression: GPL-3.0-only
License-File: LICENSE
Classifier: Operating System :: OS Independent
Classifier: Programming Language :: Python :: 3
Requires-Python: >=3.11
Requires-Dist: numpy
Requires-Dist: scipy
Provides-Extra: dev
Requires-Dist: build; extra == 'dev'
Requires-Dist: pylint; extra == 'dev'
Requires-Dist: pytest; extra == 'dev'
Requires-Dist: pytest-rerunfailures; extra == 'dev'
Requires-Dist: twine; extra == 'dev'
